{
  "unversionedId": "API/v1/users/UserInvite",
  "id": "API/v1/users/UserInvite",
  "isDocsHomePage": false,
  "title": "UserInvite",
  "description": "UserInvite",
  "source": "@site/docs\\API\\v1\\users\\UserInvite.md",
  "slug": "/API/v1/users/UserInvite",
  "permalink": "/docs/API/v1/users/UserInvite",
  "editUrl": "https://github.com/facebook/docusaurus/edit/master/website/docs/API/v1/users/UserInvite.md",
  "version": "current",
  "sidebar": "someSidebar",
  "previous": {
    "title": "UserImport",
    "permalink": "/docs/API/v1/users/UserImport"
  },
  "next": {
    "title": "GetWorkspaces",
    "permalink": "/docs/API/v1/workspaces/GetWorkspaces"
  }
}